{"status":"ok","feed":{"url":"https://medium.com/feed/@nahidhnaseem","title":"Stories by Mnmnahidh on Medium","link":"https://medium.com/@nahidhnaseem?source=rss-59b1131f4158------2","author":"","description":"Stories by Mnmnahidh on Medium","image":"https://cdn-images-1.medium.com/fit/c/150/150/0*3Px91YZSiuW8MCSJ"},"items":[{"title":"Agriconnect: Bridging Farmers and Consumers for a Sustainable Future","pubDate":"2024-07-09 14:55:31","link":"https://medium.com/@nahidhnaseem/agriconnect-bridging-farmers-and-consumers-for-a-sustainable-future-018303543ba8?source=rss-59b1131f4158------2","guid":"https://medium.com/p/018303543ba8","author":"Mnmnahidh","thumbnail":"","description":"\n<figure><img alt=\"An image depicting the blog\" src=\"https://cdn-images-1.medium.com/max/627/0*nAgXRKTDigC6GD55.png\"></figure><h3>Introduction</h3>\n<p>In today\u2019s digital age, technology has the power to transform industries and improve lives. One such area ripe for innovation is agriculture. At Agriconnect, we are committed to leveraging technology to bridge the gap between farmers and consumers, promoting sustainable agriculture and local produce. In this post, we\u2019ll explore the features and benefits of Agriconnect, and how it aims to revolutionize the agricultural landscape.</p>\n<h3>The Vision Behind Agriconnect</h3>\n<p>Agriconnect was born out of a desire to support local farmers and provide consumers with fresh, high-quality produce. Our platform connects farmers directly with consumers, eliminating middlemen and ensuring fair prices. By fostering a direct connection, we help farmers earn more while giving consumers access to fresh, locally-grown food.</p>\n<h3>Key Features of Agriconnect</h3>\n<h4>1. User-Friendly Interface</h4>\n<p>Our platform is designed with simplicity in mind. Both farmers and consumers can easily navigate the site, list products, place orders, and communicate with each other seamlessly.</p>\n<h4>2. Comprehensive Seller Dashboard</h4>\n<p>Farmers can manage their inventory, track orders, and communicate with customers through an intuitive dashboard. This feature helps farmers keep track of their sales, manage stock levels, and engage with their customer base effectively.</p>\n<h4>3. Direct Communication</h4>\n<p>We understand the importance of transparency. Agriconnect includes a chat feature that allows consumers to directly communicate with farmers. This fosters trust and provides consumers with valuable information about the products they purchase.</p>\n<h4>4. Order Management System</h4>\n<p>Our robust order management system ensures that all orders are tracked from placement to delivery. Farmers can see their total earnings, orders placed, products added, and messages received, all in one\u00a0place.</p>\n<h4>5. Pre-Order Feature</h4>\n<p>To support farmers who grow seasonal crops, we\u2019ve implemented a pre-order feature. Consumers can pre-order products, allowing farmers to plan better and ensuring they have a market for their produce when it\u2019s ready for\u00a0harvest.</p>\n<h3>Why Agriconnect?</h3>\n<p>Agriconnect is more than just a marketplace; it\u2019s a community-driven platform aimed at promoting sustainable agriculture. By supporting local farmers, we reduce the carbon footprint associated with transporting food over long distances. Our platform also empowers small-scale farmers by giving them access to a larger market, helping to improve their livelihoods.</p>\n<h3>Join Us in Our\u00a0Mission</h3>\n<p>We invite you to join Agriconnect and be a part of our mission to create a more sustainable and equitable food system. Whether you\u2019re a farmer looking to reach more customers or a consumer eager to support local agriculture, Agriconnect has something to offer\u00a0you.</p>\n<h3>Conclusion</h3>\n<p>Agriconnect is poised to make a significant impact on the agricultural industry by connecting farmers directly with consumers. Our platform promotes sustainable farming practices, supports local economies, and provides consumers with fresh, locally-sourced food. We are excited about the future of Agriconnect and the positive changes it can bring to the agricultural sector.</p>\n<p><strong>Call to Action</strong>: If you\u2019re passionate about sustainable agriculture and supporting local farmers, join us on Agriconnect today. Visit our website to learn more, sign up, and start making a difference. Together, we can build a healthier, more sustainable future.</p>\n<img src=\"https://medium.com/_/stat?event=post.clientViewed&amp;referrerSource=full_rss&amp;postId=018303543ba8\" width=\"1\" height=\"1\" alt=\"\">\n","content":"\n<figure><img alt=\"An image depicting the blog\" src=\"https://cdn-images-1.medium.com/max/627/0*nAgXRKTDigC6GD55.png\"></figure><h3>Introduction</h3>\n<p>In today\u2019s digital age, technology has the power to transform industries and improve lives. One such area ripe for innovation is agriculture. At Agriconnect, we are committed to leveraging technology to bridge the gap between farmers and consumers, promoting sustainable agriculture and local produce. In this post, we\u2019ll explore the features and benefits of Agriconnect, and how it aims to revolutionize the agricultural landscape.</p>\n<h3>The Vision Behind Agriconnect</h3>\n<p>Agriconnect was born out of a desire to support local farmers and provide consumers with fresh, high-quality produce. Our platform connects farmers directly with consumers, eliminating middlemen and ensuring fair prices. By fostering a direct connection, we help farmers earn more while giving consumers access to fresh, locally-grown food.</p>\n<h3>Key Features of Agriconnect</h3>\n<h4>1. User-Friendly Interface</h4>\n<p>Our platform is designed with simplicity in mind. Both farmers and consumers can easily navigate the site, list products, place orders, and communicate with each other seamlessly.</p>\n<h4>2. Comprehensive Seller Dashboard</h4>\n<p>Farmers can manage their inventory, track orders, and communicate with customers through an intuitive dashboard. This feature helps farmers keep track of their sales, manage stock levels, and engage with their customer base effectively.</p>\n<h4>3. Direct Communication</h4>\n<p>We understand the importance of transparency. Agriconnect includes a chat feature that allows consumers to directly communicate with farmers. This fosters trust and provides consumers with valuable information about the products they purchase.</p>\n<h4>4. Order Management System</h4>\n<p>Our robust order management system ensures that all orders are tracked from placement to delivery. Farmers can see their total earnings, orders placed, products added, and messages received, all in one\u00a0place.</p>\n<h4>5. Pre-Order Feature</h4>\n<p>To support farmers who grow seasonal crops, we\u2019ve implemented a pre-order feature. Consumers can pre-order products, allowing farmers to plan better and ensuring they have a market for their produce when it\u2019s ready for\u00a0harvest.</p>\n<h3>Why Agriconnect?</h3>\n<p>Agriconnect is more than just a marketplace; it\u2019s a community-driven platform aimed at promoting sustainable agriculture. By supporting local farmers, we reduce the carbon footprint associated with transporting food over long distances. Our platform also empowers small-scale farmers by giving them access to a larger market, helping to improve their livelihoods.</p>\n<h3>Join Us in Our\u00a0Mission</h3>\n<p>We invite you to join Agriconnect and be a part of our mission to create a more sustainable and equitable food system. Whether you\u2019re a farmer looking to reach more customers or a consumer eager to support local agriculture, Agriconnect has something to offer\u00a0you.</p>\n<h3>Conclusion</h3>\n<p>Agriconnect is poised to make a significant impact on the agricultural industry by connecting farmers directly with consumers. Our platform promotes sustainable farming practices, supports local economies, and provides consumers with fresh, locally-sourced food. We are excited about the future of Agriconnect and the positive changes it can bring to the agricultural sector.</p>\n<p><strong>Call to Action</strong>: If you\u2019re passionate about sustainable agriculture and supporting local farmers, join us on Agriconnect today. Visit our website to learn more, sign up, and start making a difference. Together, we can build a healthier, more sustainable future.</p>\n<img src=\"https://medium.com/_/stat?event=post.clientViewed&amp;referrerSource=full_rss&amp;postId=018303543ba8\" width=\"1\" height=\"1\" alt=\"\">\n","enclosure":{},"categories":["sustainable-agriculture","local-farming","ecommerce-solution","ecommerce-web-development","agritech"]}]}